Boolean_Solver-0.5.2.dist-info/DESCRIPTION.rst
Boolean_Solver-0.5.2.dist-info/METADATA
Boolean_Solver-0.5.2.dist-info/RECORD
Boolean_Solver-0.5.2.dist-info/WHEEL
Boolean_Solver-0.5.2.dist-info/metadata.json
Boolean_Solver-0.5.2.dist-info/top_level.txt
boolean_solver/__init__.py
boolean_solver/code.py
boolean_solver/code_generator.py
boolean_solver/conditions.py
boolean_solver/constants.py
boolean_solver/custom_operator.py
boolean_solver/frozen_dict.py
boolean_solver/output.py
boolean_solver/processed_conditions.py
boolean_solver/qm.py
boolean_solver/solution.py
boolean_solver/solver.py
boolean_solver/start_sample.py
boolean_solver/test_sample.py
boolean_solver/tester.py
boolean_solver/util/__init__.py
boolean_solver/util/code_dict.py
boolean_solver/util/helpers.py
boolean_solver/util/inverse_tree_set.py
boolean_solver/util/last_update_dict.py
boolean_solver/util/last_update_set.py
examples/__init__.py
examples/bowling/__init__.py
examples/bowling/start_bowling.py
examples/bowling/test_bowling_functions.py
examples/game_of_life/__init__.py
examples/game_of_life/game_of_life.py
examples/game_of_life/test_game_of_life.py
tests/__init__.py
tests/test_code.py
tests/test_code_equality.py
tests/test_code_generator.py
tests/test_conditions.py
tests/test_constants.py
tests/test_solver.py
tests/test_tester.py
tests/generated_code/__init__.py
tests/generated_code/code_functions.py
tests/generated_code/code_generator_functions.py
tests/generated_code/solver_functions.py
tests/generated_code/tester_functions.py
tests/testing_helpers/__init__.py
tests/testing_helpers/common_testing_code.py
tests/testing_helpers/constants.py
tests/util/__init__.py
tests/util/test_helpers.py
tests/util/test_inverse_lexicographical_set.py
tests/util/test_last_update_set.py
