Metadata-Version: 2.0
Name: Boolean-Solver
Version: 0.5.2
Summary: Fast development with generated boolean expressions.
Home-page: https://github.com/jisazaTappsi/BooleanSolver
Author: Juan Pablo Isaza
Author-email: biosolardecolombia@gmail.com
License: MIT
Keywords: Quine McCluskey,Boolean,code,automatic code generation,expression,Boolean expression
Platform: UNKNOWN
Classifier: Development Status :: 3 - Alpha
Classifier: License :: OSI Approved :: MIT License
Classifier: Programming Language :: Python :: 2.7
Classifier: Intended Audience :: Developers
Classifier: Topic :: Software Development :: Build Tools
